velocileptors/__init__.py
velocileptors/EPT/README.md
velocileptors/EPT/__init__.py
velocileptors/EPT/cleft_kexpanded_fftw.py
velocileptors/EPT/cleft_kexpanded_resummed_fftw.py
velocileptors/EPT/ept_fftw.py
velocileptors/EPT/ept_fullresum_fftw.py
velocileptors/EPT/ept_fullresum_varyDz_fftw.py
velocileptors/EPT/ept_fullresum_varyDz_nu_fftw.py
velocileptors/EPT/moment_expansion_fftw.py
velocileptors/EPT/velocity_moments_kexpanded_fftw.py
velocileptors/LPT/README.md
velocileptors/LPT/__init__.py
velocileptors/LPT/cleft_fftw.py
velocileptors/LPT/fourier_streaming_model_fftw.py
velocileptors/LPT/gaussian_streaming_model_fftw.py
velocileptors/LPT/lpt_rsd_fftw.py
velocileptors/LPT/moment_expansion_fftw.py
velocileptors/LPT/velocity_moments_fftw.py
velocileptors/Utils/README.md
velocileptors/Utils/__init__.py
velocileptors/Utils/gaussian_poly_extrap.py
velocileptors/Utils/loginterp.py
velocileptors/Utils/loginterp.py.old
velocileptors/Utils/pnw_dst.py
velocileptors/Utils/qfuncfft.py
velocileptors/Utils/spherical_bessel_transform.py
velocileptors/Utils/spherical_bessel_transform_fftw.py
velocileptors-2.1.dist-info/LICENSE
velocileptors-2.1.dist-info/WHEEL
velocileptors-2.1.dist-info/METADATA
velocileptors-2.1.dist-info/RECORD
