Metadata-Version: 2.1
Name: velocileptors
Version: 2.1
Summary: Code for cosmological perturbation theory
Author: Stephen Chen, Martin White, Zvonimir Vlah, Mark Maus
Maintainer: Stephen Chen
Maintainer-email: "Johannes U. Lange" <jlange@american.edu>
Requires-Python: >= 3.6
Classifier: License :: OSI Approved :: MIT License
Requires-Dist: numpy
Requires-Dist: scipy
Requires-Dist: pyfftw
Project-URL: Home, https://github.com/sfschen/velocileptors
